{"title":"web3D","date":"2023-11-08T06:19:28.214Z","updated":"2023-11-08T06:19:28.214Z","comments":true,"path":"api/pages/web3d/index.json","covers":null,"excerpt":null,"content":"<iframe  \nheight=500 \nwidth=100% \nsrc=\"https://project-iprj654b2543e375f047d68ee58a-4000.preview.node01.inscode.run/scene\"  \nframeborder=0  \nallowfullscreen>\n</iframe>\n\n\n<a href=\"https://project-iprj654b2543e375f047d68ee58a-4000.preview.node01.inscode.run/scene\" title=\"[external] [title]\" target=\"\">全屏</a>\n"}